aiofauna/__init__.py
aiofauna/__main__.py
aiofauna/client/__init__.py
aiofauna/client/api_client.py
aiofauna/client/fauna_client.py
aiofauna/data/__init__.py
aiofauna/data/document.py
aiofauna/data/exceptions.py
aiofauna/data/json.py
aiofauna/data/odm.py
aiofauna/faunadb/__init__.py
aiofauna/faunadb/errors.py
aiofauna/faunadb/objects.py
aiofauna/faunadb/page.py
aiofauna/faunadb/query.py
aiofauna/helpers.py
aiofauna/server/__init__.py
aiofauna/server/asgi.py
aiofauna/server/docs.py
aiofauna/server/router.py
aiofauna/server/server.py
aiofauna/ssr/__init__.py
aiofauna/ssr/layouts/html_layout.html
aiofauna/ssr/layouts/md_layout.html
aiofauna/ssr/renderer.py
aiofauna/utils.py
aiofauna-0.2.8.dist-info/LICENSE
aiofauna-0.2.8.dist-info/METADATA
aiofauna-0.2.8.dist-info/WHEEL
aiofauna-0.2.8.dist-info/entry_points.txt
aiofauna-0.2.8.dist-info/RECORD
