Metadata-Version: 2.1
Name: aiofauna
Version: 0.2.8
Summary: Full Stack Serverless Framework
Home-page: https://github.com/obahamonde/aiofauna
License: MIT
Author: Oscar Bahamonde
Author-email: oscar.bahamonde.dev@gmail.com
Requires-Python: >=3.8,<4.0
Classifier: License :: OSI Approved :: MIT License
Classifier: Programming Language :: Python :: 3
Classifier: Programming Language :: Python :: 3.8
Classifier: Programming Language :: Python :: 3.9
Classifier: Programming Language :: Python :: 3.10
Classifier: Programming Language :: Python :: 3.11
Requires-Dist: aiohttp (>=3.8.4,<4.0.0)
Requires-Dist: aiohttp-sse (>=2.1.0,<3.0.0)
Requires-Dist: click (>=8.1.6,<9.0.0)
Requires-Dist: gunicorn (>=21.2.0,<22.0.0)
Requires-Dist: iso8601 (>=1.1.0,<2.0.0)
Requires-Dist: jinja2 (>=3.1.2,<4.0.0)
Requires-Dist: markdown-it-py[linkify] (>=3.0.0,<4.0.0)
Requires-Dist: pydantic[dotenv] (>=1.10.7,<2.0.0)
Requires-Dist: rich (>=13.4.2,<14.0.0)
Project-URL: Repository, https://github.com/obahamonde/aiofauna
